aliyunsdkapds/__init__.py
aliyunsdkapds/request/__init__.py
aliyunsdkapds/request/v20220331/CreateFileJobRequest.py
aliyunsdkapds/request/v20220331/CreateMigrationGroupRequest.py
aliyunsdkapds/request/v20220331/CreateMigrationJobRequest.py
aliyunsdkapds/request/v20220331/CreateSurveyJobOfflineRequest.py
aliyunsdkapds/request/v20220331/CreateSurveyJobRequest.py
aliyunsdkapds/request/v20220331/DeleteMigrationGroupRequest.py
aliyunsdkapds/request/v20220331/DeleteMigrationJobRequest.py
aliyunsdkapds/request/v20220331/DeleteOssFileRequest.py
aliyunsdkapds/request/v20220331/DeleteSurveyJobRequest.py
aliyunsdkapds/request/v20220331/DeleteSurveyResourcesRequest.py
aliyunsdkapds/request/v20220331/DescribeMigrationJobConfigRequest.py
aliyunsdkapds/request/v20220331/DescribeMigrationJobCountRequest.py
aliyunsdkapds/request/v20220331/DescribeOssStsRequest.py
aliyunsdkapds/request/v20220331/DescribeSummaryByStatusAndGroupRequest.py
aliyunsdkapds/request/v20220331/DescribeSummaryByStatusRequest.py
aliyunsdkapds/request/v20220331/DescribeSurveyJobCountRequest.py
aliyunsdkapds/request/v20220331/DescribeSurveyJobRequest.py
aliyunsdkapds/request/v20220331/DescribeSurveyResourceTagRequest.py
aliyunsdkapds/request/v20220331/DescribeSurveyTemplateRequest.py
aliyunsdkapds/request/v20220331/ListMigrationJobsRequest.py
aliyunsdkapds/request/v20220331/ListRegionsRequest.py
aliyunsdkapds/request/v20220331/ListSurveyJobDownLoadJobsRequest.py
aliyunsdkapds/request/v20220331/ListSurveyJobsRequest.py
aliyunsdkapds/request/v20220331/ListSurveyResourceByMigrationGroupsRequest.py
aliyunsdkapds/request/v20220331/ListSurveyResourceConnectionsRequest.py
aliyunsdkapds/request/v20220331/ListSurveyResourceTypesRequest.py
aliyunsdkapds/request/v20220331/ListSurveyResourcesDetailRequest.py
aliyunsdkapds/request/v20220331/RecoverMigrationJobRequest.py
aliyunsdkapds/request/v20220331/StopSyncMigrationJobRequest.py
aliyunsdkapds/request/v20220331/SyncMigrationJobRequest.py
aliyun_python_sdk_apds-1.0.0.dist-info/LICENSE
aliyun_python_sdk_apds-1.0.0.dist-info/METADATA
aliyun_python_sdk_apds-1.0.0.dist-info/WHEEL
aliyun_python_sdk_apds-1.0.0.dist-info/top_level.txt
aliyun_python_sdk_apds-1.0.0.dist-info/RECORD
